rtl_generator/__init__.py
rtl_generator/arguments.py
rtl_generator/context_manager.py
rtl_generator/format.py
rtl_generator/generator.py
rtl_generator/header.py
rtl_generator/heirarchy.py
rtl_generator/languages/__init__.py
rtl_generator/languages/verilog.py
rtl_generator-1.1.0.dist-info/METADATA
rtl_generator-1.1.0.dist-info/WHEEL
rtl_generator-1.1.0.dist-info/entry_points.txt
rtl_generator-1.1.0.dist-info/licenses/LICENSE
rtl_generator-1.1.0.dist-info/RECORD
